setup.py
insight_sdk_win.egg-info/PKG-INFO
insight_sdk_win.egg-info/SOURCES.txt
insight_sdk_win.egg-info/dependency_links.txt
insight_sdk_win.egg-info/top_level.txt
insight_sdk_win/com/__init__.py
insight_sdk_win/com/data_handle.py
insight_sdk_win/com/log_handle.py
insight_sdk_win/com/insight/common.py
insight_sdk_win/com/insight/market_service.py
insight_sdk_win/com/insight/playback.py
insight_sdk_win/com/insight/query.py
insight_sdk_win/com/insight/subscribe.py
insight_sdk_win/com/interface/mdc_gateway_base_define.py
insight_sdk_win/com/interface/mdc_gateway_head.py
insight_sdk_win/com/interface/mdc_gateway_interface.py
insight_sdk_win/com/interface/mdc_recvdata_interface.py
insight_sdk_win/com/__init__.py
insight_sdk_win/com/data_handle.py
insight_sdk_win/com/log_handle.py
insight_sdk_win/com/cert/HTISCA.crt
insight_sdk_win/com/cert/HTInsightCA.crt
insight_sdk_win/com/cert/InsightClientCert.pem
insight_sdk_win/com/cert/InsightClientKeyPkcs8.pem
insight_sdk_win/com/insight/common.py
insight_sdk_win/com/insight/market_service.py
insight_sdk_win/com/insight/playback.py
insight_sdk_win/com/insight/query.py
insight_sdk_win/com/insight/subscribe.py
insight_sdk_win/com/interface/mdc_gateway_base_define.py
insight_sdk_win/com/interface/mdc_gateway_head.py
insight_sdk_win/com/interface/mdc_gateway_interface.py
insight_sdk_win/com/interface/mdc_recvdata_interface.py
insight_sdk_win/com/libs/python310/x64/ACE.dll
insight_sdk_win/com/libs/python310/x64/ACE_SSL.dll
insight_sdk_win/com/libs/python310/x64/_mdc_gateway_client.pyd
insight_sdk_win/com/libs/python310/x64/libeay32.dll
insight_sdk_win/com/libs/python310/x64/mdc_gateway_client.py
insight_sdk_win/com/libs/python310/x64/ssleay32.dll
insight_sdk_win/com/libs/python310/x86/ACE.dll
insight_sdk_win/com/libs/python310/x86/ACE_SSL.dll
insight_sdk_win/com/libs/python310/x86/_mdc_gateway_client.pyd
insight_sdk_win/com/libs/python310/x86/insight_query_client.dll
insight_sdk_win/com/libs/python310/x86/libeay32.dll
insight_sdk_win/com/libs/python310/x86/mdc_gateway_client.py
insight_sdk_win/com/libs/python310/x86/ssleay32.dll
insight_sdk_win/com/libs/python36/x64/ACE.dll
